mcl/__init__.py
mcl/__main__.py
mcl/core.py
mcl_axis-0.2.0.dist-info/LICENSE
mcl_axis-0.2.0.dist-info/METADATA
mcl_axis-0.2.0.dist-info/WHEEL
mcl_axis-0.2.0.dist-info/entry_points.txt
mcl_axis-0.2.0.dist-info/top_level.txt
mcl_axis-0.2.0.dist-info/RECORD
