Metadata-Version: 2.1
Name: mcl-axis
Version: 0.2.0
Summary: A tool to find the most common libraries used
Author: Axis (blankRiot96)
Keywords: cli,most common libraries
Classifier: License :: OSI Approved :: MIT License
Classifier: Programming Language :: Python :: 3.11
Classifier: Intended Audience :: Developers
Requires-Python: >=3.11
License-File: LICENSE
Requires-Dist: click
Requires-Dist: tabulate
Requires-Dist: libcst
